akagi/__init__.py
akagi/content.py
akagi/data_file.py
akagi/data_source.py
akagi/iterator.py
akagi/log.py
akagi/utils.py
akagi/contents/__init__.py
akagi/contents/local_file_content.py
akagi/contents/s3_content.py
akagi/contents/spreadsheet_content.py
akagi/contents/url_content.py
akagi/data_sources/__init__.py
akagi/data_sources/local_data_source.py
akagi/data_sources/redshift_data_source.py
akagi/data_sources/s3_data_source.py
akagi/data_sources/spreadsheet_data_source.py
akagi/data_sources/url_data_source.py
akagi/iterators/__init__.py
akagi/iterators/binary_iterator.py
akagi/iterators/csv_iterator.py
akagi/iterators/spreadsheet_iterator.py
akagi-0.4.1.dist-info/METADATA
akagi-0.4.1.dist-info/RECORD
akagi-0.4.1.dist-info/WHEEL
akagi-0.4.1.dist-info/top_level.txt
