Metadata-Version: 2.1
Name: akagi
Version: 0.4.1
Summary: Codenize your data sources
Home-page: https://github.com/ayemos/akagi
Author: Yuichiro Someya
Author-email: ayemos.y@gmail.com
License: MIT license
Keywords: akagi
Platform: UNKNOWN
Classifier: Development Status :: 2 - Pre-Alpha
Classifier: Intended Audience :: Developers
Classifier: License :: OSI Approved :: MIT License
Classifier: Natural Language :: English
Classifier: Programming Language :: Python :: 2
Classifier: Programming Language :: Python :: 2.7
Classifier: Programming Language :: Python :: 3
Classifier: Programming Language :: Python :: 3.4
Classifier: Programming Language :: Python :: 3.5
Requires-Dist: boto3 (>=1.4.4)
Requires-Dist: psycopg2 (>=2.7)
Requires-Dist: filetype (>=1.0.0)
Requires-Dist: google-api-python-client (>=1.6.3)
Requires-Dist: google-auth (>=1.0.2)
